neuralnetwork/Backpropagation.py
neuralnetwork/FeedForward.py
neuralnetwork/HyperbolicTangent.py
neuralnetwork/Sigmoid.py
neuralnetwork-1.8.dist-info/LICENSE.txt
neuralnetwork-1.8.dist-info/METADATA
neuralnetwork-1.8.dist-info/WHEEL
neuralnetwork-1.8.dist-info/top_level.txt
neuralnetwork-1.8.dist-info/RECORD
