Metadata-Version: 2.1
Name: neuralnetwork
Version: 1.8
Summary: Artificial Neural Network
Home-page: https://github.com/stephenlmoshea/python-neuralnetwork
Author: Stephen OShea
Author-email: stephenlmoshea@gmail.com
License: MIT
Download-URL: https://github.com/stephenlmoshea/python-neuralnetwork/archive/v1.8.tar.gz
Keywords: NEURAL NETWORK,BACKPROPAGATION,GRADIENT DESCENT,SIGMOID,HYPERBOLIC TANGENT
Platform: UNKNOWN
Classifier: Development Status :: 5 - Production/Stable
Classifier: Intended Audience :: Developers
Classifier: Topic :: Software Development :: Build Tools
Classifier: License :: OSI Approved :: MIT License
Classifier: Programming Language :: Python :: 3
Classifier: Programming Language :: Python :: 3.4
Classifier: Programming Language :: Python :: 3.5
Classifier: Programming Language :: Python :: 3.6
Requires-Dist: python-dotenv
